AUTHORS
CHANGELOG.txt
LICENSE
MANIFEST.in
README.rst
setup.py
cms/__init__.py
cms/api.py
cms/app_base.py
cms/apphook_pool.py
cms/appresolver.py
cms/cms_toolbar.py
cms/context_processors.py
cms/exceptions.py
cms/menu.py
cms/menu_bases.py
cms/plugin_base.py
cms/plugin_pool.py
cms/plugin_processors.py
cms/plugin_rendering.py
cms/signals.py
cms/urls.py
cms/views.py
cms/admin/__init__.py
cms/admin/change_list.py
cms/admin/forms.py
cms/admin/models.py
cms/admin/pageadmin.py
cms/admin/permissionadmin.py
cms/admin/placeholderadmin.py
cms/admin/useradmin.py
cms/admin/views.py
cms/admin/dialog/__init__.py
cms/admin/dialog/forms.py
cms/admin/dialog/views.py
cms/cache/__init__.py
cms/cache/permissions.py
cms/conf/__init__.py
cms/conf/global_settings.py
cms/conf/patch.py
cms/forms/__init__.py
cms/forms/fields.py
cms/forms/utils.py
cms/forms/widgets.py
cms/locale/ar/LC_MESSAGES/django.mo
cms/locale/ar/LC_MESSAGES/django.po
cms/locale/ar/LC_MESSAGES/djangojs.mo
cms/locale/ar/LC_MESSAGES/djangojs.po
cms/locale/bg/LC_MESSAGES/django.mo
cms/locale/bg/LC_MESSAGES/django.po
cms/locale/bg/LC_MESSAGES/djangojs.mo
cms/locale/bg/LC_MESSAGES/djangojs.po
cms/locale/bn/LC_MESSAGES/django.mo
cms/locale/bn/LC_MESSAGES/django.po
cms/locale/bn/LC_MESSAGES/djangojs.mo
cms/locale/bn/LC_MESSAGES/djangojs.po
cms/locale/ca/LC_MESSAGES/django.mo
cms/locale/ca/LC_MESSAGES/django.po
cms/locale/ca/LC_MESSAGES/djangojs.mo
cms/locale/ca/LC_MESSAGES/djangojs.po
cms/locale/cs/LC_MESSAGES/django.mo
cms/locale/cs/LC_MESSAGES/django.po
cms/locale/cs/LC_MESSAGES/djangojs.mo
cms/locale/cs/LC_MESSAGES/djangojs.po
cms/locale/cy/LC_MESSAGES/django.mo
cms/locale/cy/LC_MESSAGES/django.po
cms/locale/cy/LC_MESSAGES/djangojs.mo
cms/locale/cy/LC_MESSAGES/djangojs.po
cms/locale/da/LC_MESSAGES/django.mo
cms/locale/da/LC_MESSAGES/django.po
cms/locale/da/LC_MESSAGES/djangojs.mo
cms/locale/da/LC_MESSAGES/djangojs.po
cms/locale/de/LC_MESSAGES/django.mo
cms/locale/de/LC_MESSAGES/django.po
cms/locale/de/LC_MESSAGES/djangojs.mo
django_cms_patched.egg-info/PKG-INFO
django_cms_patched.egg-info/SOURCES.txt
django_cms_patched.egg-info/dependency_links.txt
django_cms_patched.egg-info/not-zip-safe
django_cms_patched.egg-info/requires.txt
django_cms_patched.egg-info/top_level.txt
