Metadata-Version: 1.0
Name: django-cms-patched
Version: 2.3.5
Summary: An Advanced Django CMS
Home-page: https://www.django-cms.org/
Author: Patrick Lauber
Author-email: digi@treepy.com
License: BSD License
Platform: OS Independent
Classifier: Development Status :: 5 - Production/Stable
Classifier: Environment :: Web Environment
Classifier: Framework :: Django
Classifier: Intended Audience :: Developers
Classifier: License :: OSI Approved :: BSD License
Classifier: Operating System :: OS Independent
Classifier: Programming Language :: Python
Classifier: Topic :: Internet :: WWW/HTTP :: Dynamic Content
Classifier: Topic :: Software Development
Classifier: Topic :: Software Development :: Libraries :: Application Frameworks
